photogrammetry/__init__.py
photogrammetry/_photogrammetry.cpython-310-x86_64-linux-gnu.h
photogrammetry/_photogrammetry.cpython-310-x86_64-linux-gnu.so
photogrammetry/build.py
photogrammetry/go.py
photogrammetry/photogrammetry.c
photogrammetry/photogrammetry.go
photogrammetry/photogrammetry.py
photogrammetry/photogrammetry_go.h
photogrammetry_tower-1.0.0.dist-info/LICENSE
photogrammetry_tower-1.0.0.dist-info/METADATA
photogrammetry_tower-1.0.0.dist-info/WHEEL
photogrammetry_tower-1.0.0.dist-info/top_level.txt
photogrammetry_tower-1.0.0.dist-info/RECORD
