Metadata-Version: 2.1
Name: photogrammetry-tower
Version: 1.0.0
Summary: Photogrammetry helper functions
Author-email: Gegeco <gegeco06@gmail.com>
License: MIT License
Project-URL: Homepage, https://github.com/gegeco/photogrammetry
Keywords: photogrammetry,3D,tower
Classifier: License :: OSI Approved :: MIT License
Classifier: Programming Language :: Python :: 3
Requires-Python: >=3.6
License-File: LICENSE
Requires-Dist: pybindgen
